raglib/__init__.py
raglib/rag.py
raglib-0.1.1.dist-info/METADATA
raglib-0.1.1.dist-info/WHEEL
raglib-0.1.1.dist-info/top_level.txt
raglib-0.1.1.dist-info/RECORD
