Metadata-Version: 2.4
Name: raglib
Version: 0.1.1
Summary: Librería para consultas RAG
Author-email: Harrison Chacon <harrisonlchr@gmail.com>
Requires-Dist: openai-agents
